<?xml version="1.0" encoding="UTF-8"?>
<GenerateModel xmlns:xsi="http://www.w3.org/2001/XMLSchema-instance" xsi:noNamespaceSchemaLocation="generateMetaModel_Module.xsd">
  <PythonExport 
	  Father="ParaGeometryPy" 
	  Name="ParaGeometry2DPy" 
	  Twin="ParaGeometry2D" 
	  TwinPointer="ParaGeometry2D" 
	  Include="Mod/ConstraintSolver/App/G2D/ParaGeometry2D.h" 
	  FatherInclude="Mod/ConstraintSolver/App/ParaGeometryPy.h" 
	  Namespace="FCS::G2D" 
	  Constructor="false"
	  Delete="false"
	  FatherNamespace="FCS"
	  DisableNotify="true">
	<Documentation>
	  <Author Licence="LGPL" Name="DeepSOIC" EMail="vv.titov@gmail.com" />
	  <DeveloperDocu>2D geometry base class</DeveloperDocu>
	  <UserDocu>2D geometry base class</UserDocu>
	</Documentation>
    
    
  </PythonExport>
</GenerateModel>
